dockup/__init__.py
dockup/__main__.py
dockup/config.py
dockup/docker_compose.py
dockup/docker_file.py
dockup/dockup.py
dockup/proxy_cfg.py
dockup/utils.py
dockup-0.0.13.dist-info/LICENSE
dockup-0.0.13.dist-info/METADATA
dockup-0.0.13.dist-info/WHEEL
dockup-0.0.13.dist-info/RECORD
